SFLvault_common-0.9.2-py3.8-nspkg.pth
sflvault/common/__init__.py
sflvault/common/crypto.py
SFLvault_common-0.9.2.dist-info/.gitignore
SFLvault_common-0.9.2.dist-info/METADATA
SFLvault_common-0.9.2.dist-info/WHEEL
SFLvault_common-0.9.2.dist-info/entry_points.txt
SFLvault_common-0.9.2.dist-info/namespace_packages.txt
SFLvault_common-0.9.2.dist-info/top_level.txt
SFLvault_common-0.9.2.dist-info/RECORD
