Metadata-Version: 2.1
Name: SFLvault-common
Version: 0.9.2
Summary: Networked credentials store and authentication manager - Common
Home-page: https://www.sflvault.org
Author: Savoir-faire Linux
Author-email: contact@savoirfairelinux.com
License: GPLv3
Platform: UNKNOWN
Requires-Dist: pycrypto
